accasim/__init__.py
accasim/base/__init__.py
accasim/base/additional_data.py
accasim/base/allocator_class.py
accasim/base/event_class.py
accasim/base/resource_manager_class.py
accasim/base/scheduler_class.py
accasim/base/simulator_class.py
accasim/experimentation/__init__.py
accasim/experimentation/experiment.py
accasim/experimentation/schedule_parser.py
accasim/experimentation/schedule_writer.py
accasim/experimentation/workload_generator.py
accasim/utils/__init__.py
accasim/utils/async_writer.py
accasim/utils/data_fitting.py
accasim/utils/file.py
accasim/utils/misc.py
accasim/utils/plot_factory.py
accasim/utils/reader_class.py
accasim/utils/visualization_class.py
accasim-1.1.3.dist-info/LICENSE
accasim-1.1.3.dist-info/LICENSE.txt
accasim-1.1.3.dist-info/METADATA
accasim-1.1.3.dist-info/WHEEL
accasim-1.1.3.dist-info/top_level.txt
accasim-1.1.3.dist-info/RECORD
