Metadata-Version: 2.1
Name: accasim
Version: 1.1.3
Summary: An HPC Workload Management Simulator
Home-page: http://accasim.readthedocs.io/en/latest/
Author: Cristian Galleguillos
Author-email: cristian.galleguillos.m@mail.pucv.cl
License: MIT
Keywords: research,hpc,dispathing
Platform: UNKNOWN
Classifier: Development Status :: 5 - Production/Stable
Classifier: Intended Audience :: Science/Research
Classifier: Topic :: Scientific/Engineering
Classifier: License :: OSI Approved :: MIT License
Classifier: Programming Language :: Python :: 3.5
Classifier: Programming Language :: Python :: 3.6
Requires-Python: >=3.4
License-File: LICENSE.txt
License-File: LICENSE
Requires-Dist: matplotlib
Requires-Dist: psutil
Requires-Dist: sortedcontainers
Requires-Dist: numpy (>=1.6)
Requires-Dist: scipy (>=1.0)
